brille/COPYING
brille/__init__.py
brille/_brille.cpython-313-x86_64-linux-gnu.so
brille/bound.py
brille/lattice.py
brille/plotting.py
brille/utils.py
brille/vis.py
brille.libs/libgomp-870cb1d0.so.1.0.0
brille-0.8.3.dist-info/METADATA
brille-0.8.3.dist-info/WHEEL
brille-0.8.3.dist-info/RECORD
brille-0.8.3.dist-info/licenses/COPYING
brille-0.8.3.dist-info/licenses/lib/hdf5/LICENSE
brille-0.8.3.dist-info/licenses/lib/tetgen/LICENSE
