Metadata-Version: 2.4
Name: brille
Version: 0.8.3
Summary: Irreducible Brillouin zone symmetry and interpolation.
Author: Gregory Tucker, Duc Le, Rebecca Fair
Maintainer-Email: Gregory Tucker <gregory.tucker@ess.eu>
License-Expression: AGPL-3.0-or-later
License-File: COPYING
License-File: lib/hdf5/LICENSE
License-File: lib/tetgen/LICENSE
Classifier: Development Status :: 3 - Alpha
Classifier: Intended Audience :: Science/Research
Classifier: Operating System :: Microsoft :: Windows :: Windows 10
Classifier: Operating System :: POSIX :: Linux
Classifier: Operating System :: MacOS :: MacOS X
Classifier: Programming Language :: C++
Classifier: Programming Language :: Python :: 3
Classifier: Programming Language :: Python :: 3 :: Only
Classifier: Programming Language :: Python :: 3.10
Classifier: Programming Language :: Python :: 3.11
Classifier: Programming Language :: Python :: 3.12
Classifier: Programming Language :: Python :: 3.13
Classifier: Programming Language :: Python :: 3.14
Classifier: Topic :: Scientific/Engineering :: Physics
Project-URL: Homepage, https://github.com/brille
Project-URL: Documentation, https://brille.github.io
Project-URL: Respository, https://github.com/brille/brille.git
Project-URL: Issues, https://github.com/brille/brille/issues
Requires-Python: >=3.10
Requires-Dist: numpy
Provides-Extra: plotting
Requires-Dist: matplotlib>=2.2.0; extra == "plotting"
Provides-Extra: vis
Requires-Dist: pyglet>=1.5.27; extra == "vis"
Requires-Dist: vispy>=0.12.1; extra == "vis"
